DreamScreenWeatherApp/__init__.py
DreamScreenWeatherApp/configure.py
DreamScreenWeatherApp/info.py
DreamScreenWeatherApp/service.py
DreamScreenWeatherApp-0.10.dist-info/METADATA
DreamScreenWeatherApp-0.10.dist-info/WHEEL
DreamScreenWeatherApp-0.10.dist-info/top_level.txt
DreamScreenWeatherApp-0.10.dist-info/RECORD
