Metadata-Version: 2.1
Name: DreamScreenWeatherApp
Version: 0.10
Summary: An interface to Weather Underground, as a data source for the HP DreamScreen weather app.
Home-page: https://bitbucket.org/jtashiro/dreamscreen-weather/src/master/
Author: John Tashiro
Author-email: jtashiro@fiospace.com
License: UNKNOWN
Platform: UNKNOWN
Classifier: Programming Language :: Python :: 3
Classifier: License :: OSI Approved :: MIT License
Classifier: Operating System :: OS Independent
Requires-Python: >=2.7
